[
  {
    "name": "皇帝聖印戰記",
    "type": "歷史傳記",
    "ep": 24,
    "view": 1100000,
    "image": "https://p2.bahamut.com.tw/B/ACG/c/33/0000085733.JPG",
    "sn": "85733",
    "view_avg": 45833.33,
    "year": 2018,
    "month": 1
  },
  {
    "name": "阿爾蒂",
    "type": "歷史傳記",
    "ep": 12,
    "view": 524000,
    "image": "https://p2.bahamut.com.tw/B/ACG/c/28/0000106728.JPG",
    "sn": "106728",
    "view_avg": 43666.67,
    "year": 2020,
    "month": 4
  },
  {
    "name": "王者天下 第三季",
    "type": "歷史傳記",
    "ep": 12,
    "view": 509000,
    "image": "https://p2.bahamut.com.tw/B/ACG/c/06/0000108606.JPG",
    "sn": "108606",
    "view_avg": 42416.67,
    "year": 2020,
    "month": 4
  },
  {
    "name": "胡蝶綺～少年信長～",
    "type": "歷史傳記",
    "ep": 12,
    "view": 212000,
    "image": "https://p2.bahamut.com.tw/B/ACG/c/93/0000103193.JPG",
    "sn": "103193",
    "view_avg": 17666.67,
    "year": 2019,
    "month": 7
  },
  {
    "name": "刀劍亂舞 - 花丸 - ～幕間回憶錄～",
    "type": "歷史傳記",
    "ep": 1,
    "view": 15000,
    "image": "https://p2.bahamut.com.tw/B/ACG/c/70/0000103470.JPG",
    "sn": "103470",
    "view_avg": 15000,
    "year": 2017,
    "month": 12
  },
  {
    "name": "王者天下",
    "type": "歷史傳記",
    "ep": 39,
    "view": 556000,
    "image": "https://p2.bahamut.com.tw/B/ACG/c/52/0000053052.JPG",
    "sn": "53052",
    "view_avg": 14256.41,
    "year": 2012,
    "month": 6
  },
  {
    "name": "王者天下 第二季",
    "type": "歷史傳記",
    "ep": 39,
    "view": 520000,
    "image": "https://p2.bahamut.com.tw/B/ACG/c/78/0000061678.JPG",
    "sn": "61678",
    "view_avg": 13333.33,
    "year": 2013,
    "month": 6
  },
  {
    "name": "活擊 刀劍亂舞",
    "type": "歷史傳記",
    "ep": 13,
    "view": 150000,
    "image": "https://p2.bahamut.com.tw/B/ACG/c/53/0000086753.JPG",
    "sn": "86753",
    "view_avg": 11538.46,
    "year": 2017,
    "month": 7
  },
  {
    "name": "刀劍亂舞 - 花丸 - 續篇",
    "type": "歷史傳記",
    "ep": 12,
    "view": 122000,
    "image": "https://p2.bahamut.com.tw/B/ACG/c/60/0000087360.JPG",
    "sn": "87360",
    "view_avg": 10166.67,
    "year": 2018,
    "month": 1
  },
  {
    "name": "Angolmois 元寇合戰記",
    "type": "歷史傳記",
    "ep": 12,
    "view": 101000,
    "image": "https://p2.bahamut.com.tw/B/ACG/c/89/0000095889.JPG",
    "sn": "95889",
    "view_avg": 8416.67,
    "year": 2018,
    "month": 7
  },
  {
    "name": "神劍闖江湖",
    "type": "歷史傳記",
    "ep": 94,
    "view": 777000,
    "image": "https://p2.bahamut.com.tw/B/ACG/c/67/0000000167.JPG",
    "sn": "167",
    "view_avg": 8265.96,
    "year": 1996,
    "month": 1
  },
  {
    "name": "神劍闖江湖 星霜篇",
    "type": "歷史傳記",
    "ep": 2,
    "view": 13000,
    "image": "https://p2.bahamut.com.tw/B/ACG/c/44/0000024344.JPG",
    "sn": "24344",
    "view_avg": 6500,
    "year": 2001,
    "month": 12
  },
  {
    "name": "尤利西斯 貞德與鍊金騎士",
    "type": "歷史傳記",
    "ep": 12,
    "view": 49000,
    "image": "https://p2.bahamut.com.tw/B/ACG/c/22/0000097522.JPG",
    "sn": "112506",
    "view_avg": 4083.33,
    "year": 2018,
    "month": 10
  },
  {
    "name": "喵的咧～貓咪戲說日本史！第四季",
    "type": "歷史傳記",
    "ep": 32,
    "view": 4258,
    "image": "https://p2.bahamut.com.tw/B/ACG/c/37/0000117637.JPG",
    "sn": "112712",
    "view_avg": 133.06,
    "year": 2019,
    "month": 4
  }
]